fabricclientaio/__init__.py
fabricclientaio/auth/__init__.py
fabricclientaio/auth/fabrictokenprovider.py
fabricclientaio/error.py
fabricclientaio/fabricclient.py
fabricclientaio/fabriccoreclient.py
fabricclientaio/fabricworkspaceclient.py
fabricclientaio/models/__init__.py
fabricclientaio/models/responses.py
fabricclientaio/py.typed
fabricclientaio/utils/__init__.py
fabricclientaio/utils/timeutils.py
fabricclientaio-0.1.0.dist-info/METADATA
fabricclientaio-0.1.0.dist-info/WHEEL
fabricclientaio-0.1.0.dist-info/RECORD
