Metadata-Version: 2.1
Name: fabricclientaio
Version: 0.1.0
Summary: 
Author: Austin M. Reppert
Author-email: austinmreppert@gmail.com
Requires-Python: >=3.11
Classifier: Programming Language :: Python :: 3
Classifier: Programming Language :: Python :: 3.11
Classifier: Programming Language :: Python :: 3.12
Requires-Dist: aiohttp (>=3.9.5,<4.0.0)
Requires-Dist: azure-identity (>=1.17.1,<2.0.0)
Requires-Dist: pydantic (>=2.8.2,<3.0.0)
